probeX/__init__.py
probeX/start.py
probeX/framework/__init__.py
probeX/framework/api/__init__.py
probeX/framework/client/HTTPClient.py
probeX/framework/client/KubernetesClient.py
probeX/framework/client/MysqlClient.py
probeX/framework/client/__init__.py
probeX/framework/config/Config.py
probeX/framework/config/__init__.py
probeX/framework/config/env.py
probeX/framework/config/environment.py
probeX/framework/entity/AirsAPI.py
probeX/framework/entity/__init__.py
probeX/framework/model/BaseModel.py
probeX/framework/model/BaseUser.py
probeX/framework/model/__init__.py
probeX/framework/schedule/__init__.py
probeX/framework/schedule/case_schedule.py
probeX/framework/schedule/context.py
probeX/framework/schedule/dependency_graph.py
probeX/framework/schedule/executor.py
probeX/framework/schedule/test_task.py
probeX/framework/service/__init__.py
probeX/framework/service/case_service.py
probeX/framework/service/kube_service.py
probeX/framework/service/report_serve_service.py
probeX/framework/service/swagger_service.py
probeX/framework/service/user_service.py
probeX/framework/utils/ApiConfigLoader.py
probeX/framework/utils/OTP.py
probeX/framework/utils/SwaggerParse.py
probeX/framework/utils/log.py
probeX/framework/utils/reporter.py
probeX/framework/utils/test_data_loader.py
probeX/framework/utils/utils.py
probeX/probeX-backend/app.py
probeX/probeX-backend/server.py
probeX/probeX-backend/config/constant.py
probeX/probeX-backend/config/database.py
probeX/probeX-backend/config/enums.py
probeX/probeX-backend/config/env.py
probeX/probeX-backend/config/get_db.py
probeX/probeX-backend/config/get_redis.py
probeX/probeX-backend/config/get_scheduler.py
probeX/probeX-backend/exceptions/exception.py
probeX/probeX-backend/exceptions/handle.py
probeX/probeX-backend/middlewares/cors_middleware.py
probeX/probeX-backend/middlewares/gzip_middleware.py
probeX/probeX-backend/middlewares/handle.py
probeX/probeX-backend/module_admin/annotation/log_annotation.py
probex-0.1.3.dist-info/licenses/LICENSE
probex-0.1.3.dist-info/METADATA
probex-0.1.3.dist-info/WHEEL
probex-0.1.3.dist-info/entry_points.txt
probex-0.1.3.dist-info/top_level.txt
probex-0.1.3.dist-info/RECORD
