Metadata-Version: 2.4
Name: probeX
Version: 0.1.3
Summary: A sample project for pytest
Author-email: gavin <yangguangyu_cn@163.com>
License-Expression: MIT
Project-URL: Homepage, https://github.com/
License-File: LICENSE
Dynamic: license-file
